{
    "original_filename": "customer churn.csv",
    "stored_filename": "20260429_163447_ffafe6c3_customer churn.csv",
    "stored_path": "data\\raw\\20260429_163447_ffafe6c3_customer churn.csv",
    "version_id": "ffafe6c3",
    "timestamp": "20260429_163447",
    "file_type": ".csv",
    "rows": 7043,
    "columns_count": 21,
    "columns": [
        "customerID",
        "gender",
        "SeniorCitizen",
        "Partner",
        "Dependents",
        "tenure",
        "PhoneService",
        "MultipleLines",
        "InternetService",
        "OnlineSecurity",
        "OnlineBackup",
        "DeviceProtection",
        "TechSupport",
        "StreamingTV",
        "StreamingMovies",
        "Contract",
        "PaperlessBilling",
        "PaymentMethod",
        "MonthlyCharges",
        "TotalCharges",
        "Churn"
    ]
}